intra42api/__init__.py
intra42api/intra42.py
intra42api-0.0.1.dist-info/LICENCE.txt
intra42api-0.0.1.dist-info/METADATA
intra42api-0.0.1.dist-info/WHEEL
intra42api-0.0.1.dist-info/top_level.txt
intra42api-0.0.1.dist-info/RECORD
