Metadata-Version: 2.1
Name: intra42api
Version: 0.0.1
Summary: 42Network API Wrapper
Home-page: 
Author: Nasroallah El Idrissi
Author-email: nelidris@student.1337.ma
License: MIT
Keywords: API Wrapper,42Network
Platform: UNKNOWN
Classifier: Intended Audience :: Developers
Classifier: License :: OSI Approved :: MIT License
Classifier: Natural Language :: English
Classifier: Programming Language :: Python :: 3.6
Classifier: Programming Language :: Python :: 3.7
Classifier: Programming Language :: Python :: 3.8
Classifier: Programming Language :: Python :: 3.9
Classifier: Topic :: Internet
Classifier: Topic :: Utilities
Classifier: Topic :: Software Development :: Libraries
Classifier: Topic :: Software Development :: Libraries :: Python Modules
License-File: LICENCE.txt
Requires-Dist: requests
